yt_dlp_plugins/extractor/streamingcommunity.py
streaming_fetcher/__init__.py
streaming_fetcher/exceptions.py
streaming_fetcher/fetch_task/__init__.py
streaming_fetcher/fetch_task/anime_unity.py
streaming_fetcher/fetch_task/episode_fetch_task.py
streaming_fetcher/fetch_task/fetch_task.py
streaming_fetcher/fetch_task/fetch_task_configuration.py
streaming_fetcher/fetch_task/streaming_community.py
streaming_fetcher/streaming_fetcher.py
streaming_fetcher/utils/__init__.py
streaming_fetcher/utils/make_standard_path.py
streaming_fetcher/utils/playwright_utils.py
streaming_fetcher-0.3.0.dist-info/METADATA
streaming_fetcher-0.3.0.dist-info/WHEEL
streaming_fetcher-0.3.0.dist-info/licenses/LICENSE
streaming_fetcher-0.3.0.dist-info/RECORD
