Metadata-Version: 2.4
Name: streaming-fetcher
Version: 0.3.0
Summary: Streaming fetcher library can be used to automatize downloads from streaming sites
License: GPL-3.0-or-later
License-File: LICENSE
Author: Roberto Bochet
Author-email: r@robertobochet.me
Requires-Python: >=3.13,<4.0
Classifier: Development Status :: 5 - Production/Stable
Classifier: Framework :: AsyncIO
Classifier: License :: OSI Approved :: GNU General Public License v3 or later (GPLv3+)
Classifier: Operating System :: OS Independent
Classifier: Programming Language :: Python :: 3
Classifier: Programming Language :: Python :: 3.13
Classifier: Programming Language :: Python :: 3.14
Classifier: Topic :: Multimedia :: Video
Classifier: Topic :: Software Development :: Libraries
Classifier: Typing :: Typed
Requires-Dist: playwright (>=1.55.0,<2.0.0)
Requires-Dist: python-dateutil (>=2.9.0.post0,<3.0.0)
Requires-Dist: yt-dlp (>=2025.10.22,<2026.0.0)
Project-URL: Repository, https://github.com/RobertoBochet/streaming-fetcher.git
